my_package/__init__.py
my_package/model.py
my_package/analysis/__init__.py
my_package/analysis/visualize.py
my_package/data/__init__.py
my_package/data/dataset.py
my_package/data/transforms/__init__.py
my_package/data/transforms/blur.py
my_package/data/transforms/crop.py
my_package/data/transforms/flip.py
my_package/data/transforms/rescale.py
my_package/data/transforms/rotate.py
objectdetectionmodelamit-0.1.dist-info/Licence.txt
objectdetectionmodelamit-0.1.dist-info/METADATA
objectdetectionmodelamit-0.1.dist-info/WHEEL
objectdetectionmodelamit-0.1.dist-info/top_level.txt
objectdetectionmodelamit-0.1.dist-info/RECORD
