Metadata-Version: 2.1
Name: objectdetectionmodelamit
Version: 0.1
Summary: This package helps in object detection
Home-page: UNKNOWN
Author: Amit Kumar
Author-email: ramanujaamit@gmail.com
License: UNKNOWN
Platform: UNKNOWN
Classifier: Programming Language :: Python :: 3
Classifier: License :: OSI Approved :: MIT License
Classifier: Operating System :: OS Independent
